genshin/__init__.py
genshin/__main__.py
genshin/client/__init__.py
genshin/client/cache.py
genshin/client/clients.py
genshin/client/compatibility.py
genshin/client/components/__init__.py
genshin/client/components/auth/__init__.py
genshin/client/components/auth/client.py
genshin/client/components/auth/server.py
genshin/client/components/auth/subclients/__init__.py
genshin/client/components/auth/subclients/app.py
genshin/client/components/auth/subclients/game.py
genshin/client/components/auth/subclients/web.py
genshin/client/components/base.py
genshin/client/components/calculator/__init__.py
genshin/client/components/calculator/calculator.py
genshin/client/components/calculator/client.py
genshin/client/components/chronicle/__init__.py
genshin/client/components/chronicle/base.py
genshin/client/components/chronicle/client.py
genshin/client/components/chronicle/genshin.py
genshin/client/components/chronicle/honkai.py
genshin/client/components/chronicle/starrail.py
genshin/client/components/chronicle/zzz.py
genshin/client/components/daily.py
genshin/client/components/diary.py
genshin/client/components/gacha.py
genshin/client/components/hoyolab.py
genshin/client/components/hsr_lineup.py
genshin/client/components/lineup.py
genshin/client/components/teapot.py
genshin/client/components/transaction.py
genshin/client/components/wiki.py
genshin/client/manager/__init__.py
genshin/client/manager/cookie.py
genshin/client/manager/managers.py
genshin/client/ratelimit.py
genshin/client/routes.py
genshin/constants.py
genshin/errors.py
genshin/models/__init__.py
genshin/models/auth/__init__.py
genshin/models/auth/cookie.py
genshin/models/auth/geetest.py
genshin/models/auth/qrcode.py
genshin/models/auth/responses.py
genshin/models/auth/verification.py
genshin/models/genshin/__init__.py
genshin/models/genshin/calculator.py
genshin/models/genshin/character.py
genshin/models/genshin/chronicle/__init__.py
genshin/models/genshin/chronicle/abyss.py
genshin-1.7.23.dist-info/WHEEL
genshin-1.7.23.dist-info/METADATA
genshin-1.7.23.dist-info/RECORD
