Metadata-Version: 2.3
Name: genshin
Version: 1.7.23
Summary: API wrapper for HoYoLAB/Miyoushe API built on asyncio and pydantic.
Author: ashleney
Author-email: ashleney <thesadru@gmail.com>
License: MIT License
Classifier: Development Status :: 4 - Beta
Classifier: License :: OSI Approved :: MIT License
Classifier: Intended Audience :: Developers
Classifier: Natural Language :: English
Classifier: Operating System :: OS Independent
Classifier: Programming Language :: Python
Classifier: Topic :: Internet :: WWW/HTTP
Classifier: Topic :: Software Development :: Libraries
Classifier: Topic :: Software Development :: Libraries :: Python Modules
Classifier: Topic :: Utilities
Classifier: Typing :: Typed
Requires-Dist: aiohttp==3.*
Requires-Dist: pydantic==2.*
Requires-Dist: tenacity==9.*
Requires-Dist: aiohttp-socks>=0.9.0 ; extra == 'all'
Requires-Dist: aioredis>=2.0.1 ; extra == 'all'
Requires-Dist: aiosqlite>=0.17.0 ; extra == 'all'
Requires-Dist: browser-cookie3>=0.19.1 ; extra == 'all'
Requires-Dist: click>=8.1.7 ; extra == 'all'
Requires-Dist: qrcode[pil]>=7.4.2 ; extra == 'all'
Requires-Dist: rsa>=4.9 ; extra == 'all'
Requires-Dist: qrcode[pil]>=7.4.2 ; extra == 'auth'
Requires-Dist: rsa>=4.9 ; extra == 'auth'
Requires-Dist: click>=8.1.7 ; extra == 'cli'
Requires-Dist: browser-cookie3>=0.19.1 ; extra == 'cookies'
Requires-Dist: aioredis>=2.0.1 ; extra == 'redis'
Requires-Dist: aiohttp-socks>=0.9.0 ; extra == 'socks-proxy'
Requires-Dist: aiosqlite>=0.17.0 ; extra == 'sqlite'
Maintainer: seriaati
Maintainer-email: seriaati <seriaati@gmail.com>
Requires-Python: >=3.9
Project-URL: Homepage, https://github.com/seriaati/genshin.py
Project-URL: Documentation, https://seriaati.github.io/genshin.py
Project-URL: Repository, https://github.com/seriaati/genshin.py.git
Project-URL: Issues, https://github.com/seriaati/genshin.py/issues
Provides-Extra: all
Provides-Extra: auth
Provides-Extra: cli
Provides-Extra: cookies
Provides-Extra: redis
Provides-Extra: socks-proxy
Provides-Extra: sqlite
